import_01/Q1_and_or.py
import_01/Q2_xor_andnot.py
import_01/Q3_hebbian_net.py
import_01/Q4_discrete_hopfield_net.py
import_01/Q5_Kohonen_self_organizing_maps.py
import_01/Q6_perceptron.py
import_01/Q7_lvq.py
import_01/Q8_bipolar_sigmoid.py
import_01/__init__.py
import_01/ann.py
import_01/clustering.py
import_01/code.py
import_01/lightgbm.py
import_01/main.py
import_01/modules.py
import_01/randomforest.py
import_01/whatsapp.py
import_01/xgboost.py
import_01-1.2.dist-info/LICENSE
import_01-1.2.dist-info/METADATA
import_01-1.2.dist-info/WHEEL
import_01-1.2.dist-info/top_level.txt
import_01-1.2.dist-info/RECORD
