Metadata-Version: 2.1
Name: import_01
Version: 1.2
Summary: A small example package
Home-page: https://github.com/pypa/sampleproject
Author: prnjl
Author-email: author@example.com
Project-URL: Bug Tracker, https://github.com/pypa/sampleproject/issues
Classifier: Programming Language :: Python :: 3
Classifier: License :: OSI Approved :: MIT License
Classifier: Operating System :: OS Independent
Requires-Python: >=3.6
License-File: LICENSE
